cuda_available/__init__.py
cuda_available/_core.py
cuda_available/_cuda_loader.py
cuda_available/cuda_error.py
cuda_available-0.3.1.dist-info/LICENSE
cuda_available-0.3.1.dist-info/WHEEL
cuda_available-0.3.1.dist-info/METADATA
cuda_available-0.3.1.dist-info/RECORD
